Metadata-Version: 2.1
Name: oneNeuron-pypi-kokila0602
Version: 0.0.2
Summary: its an implimentaion of perceptron
Home-page: https://github.com/kokila0602/oneNeuron_pypi
Author: USER_NAME
Author-email: kokila0602@gmail.com
License: UNKNOWN
Project-URL: Bug Tracker, https://github.com/kokila0602/oneNeuron_pypi/issues
Platform: UNKNOWN
Classifier: Programming Language :: Python :: 3
Classifier: License :: OSI Approved :: MIT License
Classifier: Operating System :: OS Independent
Requires-Python: >=3.7
License-File: LICENSE
Requires-Dist: numpy
Requires-Dist: tqdm
